fastformers/__init__.py
fastformers/_version.py
fastformers/run_model_fleet.py
fastformers/models/__init__.py
fastformers/models/bart.py
fastformers/models/bert.py
fastformers/models/blender.py
fastformers/models/distilbert.py
fastformers/models/electra.py
fastformers/models/roberta.py
fastformers/models/t5.py
fastformers/models/coref/__init__.py
fastformers/models/coref/coref.py
fastformers/models/coref/coref_utils.py
fastformers/models/coref/feed_forward.py
fastformers/models/coref/gated_sum.py
fastformers/models/coref/span_extractors.py
fastformers/models/coref/time_distributed.py
fastformers/models/coref/transformer_embedder.py
fastformers/modules/__init__.py
fastformers/modules/attention.py
fastformers/modules/base_modules.py
fastformers/modules/embeddings.py
fastformers/modules/feed_forward.py
fastformers/modules/heads.py
fastformers/modules/transformer_decoder.py
fastformers/modules/transformer_encoder.py
fastformers/multiprocess_api/__init__.py
fastformers/multiprocess_api/client_api.py
fastformers/multiprocess_api/configs.py
fastformers/multiprocess_api/model_deployment_config.py
fastformers/multiprocess_api/model_server.py
fastformers/multiprocess_api/socket_connection.py
fastformers/utils/__init__.py
fastformers/utils/logger.py
fastformers/utils/torch_utils.py
fastformers-0.0.105.dist-info/LICENSE
fastformers-0.0.105.dist-info/METADATA
fastformers-0.0.105.dist-info/WHEEL
fastformers-0.0.105.dist-info/top_level.txt
fastformers-0.0.105.dist-info/RECORD
