Metadata-Version: 2.1
Name: fastformers
Version: 0.0.105
Summary: UNKNOWN
Home-page: UNKNOWN
Author: datarootlabs
Author-email: dev@datarootlabs.com
License: UNKNOWN
Platform: UNKNOWN
Classifier: Intended Audience :: Developers
Classifier: Intended Audience :: Education
Classifier: Intended Audience :: Science/Research
Classifier: License :: OSI Approved :: Apache Software License
Classifier: Operating System :: OS Independent
Classifier: Programming Language :: Python :: 3
Classifier: Topic :: Scientific/Engineering :: Artificial Intelligence
Requires-Python: >=3.6
License-File: LICENSE
Requires-Dist: torch (>=1.6)
